{
    "2026-01-09": {
        "What are you grateful for?": "",
        "Did you exercise?": "",
        "Plan for tomorrow?": "nothing ",
        "Level of happiness (1-10)?": "9",
        "Level of stress (1-10)?": "5",
        "Who did you meet?": "gud",
        "What did you learn?": "gud",
        "What were your expenses?": "gud",
        "What did you do today?": "gud",
        "How was your day?": "awesome"
    },
    "2026-01-10": {
        "What are you grateful for?": "",
        "Did you exercise?": "",
        "Plan for tomorrow?": "",
        "Level of happiness (1-10)?": "",
        "Level of stress (1-10)?": "",
        "Who did you meet?": "",
        "What did you learn?": "",
        "What were your expenses?": "",
        "What did you do today?": "",
        "How was your day?": ""
    },
    "2026-01-08": {
        "What are you grateful for?": "",
        "Did you exercise?": "",
        "Plan for tomorrow?": "",
        "Level of happiness (1-10)?": "",
        "Level of stress (1-10)?": "",
        "Who did you meet?": "gud",
        "What did you learn?": "",
        "What were your expenses?": "",
        "What did you do today?": "",
        "How was your day?": ""
    },
    "2026-01-07": {
        "What are you grateful for?": "",
        "Did you exercise?": "",
        "Plan for tomorrow?": "",
        "Level of happiness (1-10)?": "",
        "Level of stress (1-10)?": "",
        "Who did you meet?": "",
        "What did you learn?": "",
        "What were your expenses?": "",
        "What did you do today?": "",
        "How was your day?": ""
    },
    "2026-01-11": {
        "Plan for tomorrow?": "",
        "Level of happiness (1-10)?": "",
        "Level of stress (1-10)?": "",
        "Who did you meet?": "",
        "What did you learn?": "",
        "What were your expenses?": "",
        "What did you do today?": "",
        "How was your day?": ""
    },
    "2026-01-12": {
        "Plan for tomorrow?": "",
        "Level of happiness (1-10)?": "",
        "Level of stress (1-10)?": "",
        "Who did you meet?": "",
        "What did you learn?": "",
        "What were your expenses?": "",
        "What did you do today?": "",
        "How was your day?": ""
    }
}